[
  {
    "id": 1,
    "image": "assets/images/pinot.webp",
    "wine": "PINOT NOIR",
    "year": "2019",
    "description": "výběr z hroznů, suché",
    "route": "viniční trať: Novosady",
    "name": "Víno Hradil",
    "logo": "assets/images/12LogoHradil.png",
    "site": "https://vino-hradil.cz/produkt/pinot-noir/"
  },
  {
    "id": 2,
    "image": "assets/images/pinot.webp",
    "wine": "PINOT NOIR",
    "year": "2019",
    "description": "výběr z hroznů, suché",
    "route": "viniční trať: Novosady",
    "name": "Víno Hradil",
    "logo": "assets/images/12LogoHradil.png",
    "site": "https://vino-hradil.cz/produkt/pinot-noir/"
  },
  {
    "id": 3,
    "image": "assets/images/pinot.webp",
    "wine": "PINOT NOIR",
    "year": "2019",
    "description": "výběr z hroznů, suché",
    "route": "viniční trať: Novosady",
    "name": "Víno Hradil",
    "logo": "assets/images/12LogoHradil.png",
    "site": "https://vino-hradil.cz/produkt/pinot-noir/"
  },
  {
    "id": 4,
    "image": "assets/images/pinot.webp",
    "wine": "PINOT NOIR",
    "year": "2019",
    "description": "výběr z hroznů, suché",
    "route": "viniční trať: Novosady",
    "name": "Víno Hradil",
    "logo": "assets/images/12LogoHradil.png",
    "site": "https://vino-hradil.cz/produkt/pinot-noir/"
  },
  {
    "id": 5,
    "image": "assets/images/pinot.webp",
    "wine": "PINOT NOIR",
    "year": "2019",
    "description": "výběr z hroznů, suché",
    "route": "viniční trať: Novosady",
    "name": "Víno Hradil",
    "logo": "assets/images/12LogoHradil.png",
    "site": "https://vino-hradil.cz/produkt/pinot-noir/"
  }
]
